odoo/addons/server_action_logging/README.rst
odoo/addons/server_action_logging/__init__.py
odoo/addons/server_action_logging/__manifest__.py
odoo/addons/server_action_logging/i18n/fr.po
odoo/addons/server_action_logging/i18n/it.po
odoo/addons/server_action_logging/i18n/pt_BR.po
odoo/addons/server_action_logging/i18n/server_action_logging.pot
odoo/addons/server_action_logging/models/__init__.py
odoo/addons/server_action_logging/models/ir_actions_server.py
odoo/addons/server_action_logging/readme/CONTRIBUTORS.md
odoo/addons/server_action_logging/readme/DESCRIPTION.md
odoo/addons/server_action_logging/readme/USAGE.md
odoo/addons/server_action_logging/static/description/icon.png
odoo/addons/server_action_logging/static/description/index.html
odoo/addons/server_action_logging/tests/__init__.py
odoo/addons/server_action_logging/tests/test_server_action_logging.py
odoo/addons/server_action_logging/views/ir_actions_server.xml
odoo_addon_server_action_logging-17.0.1.0.0.8.dist-info/METADATA
odoo_addon_server_action_logging-17.0.1.0.0.8.dist-info/WHEEL
odoo_addon_server_action_logging-17.0.1.0.0.8.dist-info/top_level.txt
odoo_addon_server_action_logging-17.0.1.0.0.8.dist-info/RECORD
