Metadata-Version: 2.1
Name: odoo-addon-server_action_logging
Version: 17.0.1.0.0.8
Requires-Python: >=3.10
Requires-Dist: odoo>=17.0a,<17.1dev
Summary: Module that provides a logging mechanism for server actions
Home-page: https://github.com/OCA/server-tools
License: LGPL-3
Author: Camptocamp, Odoo Community Association (OCA)
Author-email: support@odoo-community.org
Classifier: Programming Language :: Python
Classifier: Framework :: Odoo
Classifier: Framework :: Odoo :: 17.0
Classifier: License :: OSI Approved :: GNU Lesser General Public License v3 (LGPLv3)
